cry/__init__.py
cry/env.py
cry/eq/__init__.py
cry/eq/affine.py
cry/eq/draft_linear_precomp.py
cry/eq/interpolator.py
cry/eq/lattice.py
cry/fields/__init__.py
cry/fields/basis_change.py
cry/matrix.py
cry/perm.py
cry/plots.py
cry/py/__init__.py
cry/py/anf/__init__.py
cry/py/anf/mobius.py
cry/py/anf/symbolic.py
cry/py/containers/__init__.py
cry/py/containers/rect.py
cry/py/containers/vector.py
cry/py/env.py
cry/py/tree/__init__.py
cry/py/tree/anf.py
cry/py/tree/node/__init__.py
cry/py/tree/node/bitnode.py
cry/py/tree/node/node.py
cry/py/tree/node/op.py
cry/py/tree/node/optbitnode.py
cry/py/tree/node/utils.py
cry/py/tree/orderer.py
cry/py/tree/trace.py
cry/py/utils/__init__.py
cry/py/utils/cache.py
cry/rsa/rsa.py
cry/sagestuff.py
cry/sbox2/Makefile
cry/sbox2/__init__.py
cry/sbox2/algorithms/__init__.py
cry/sbox2/algorithms/multiset.py
cry/sbox2/ddt
cry/sbox2/ddt_fast.cpp
cry/sbox2/equiv/__init__.py
cry/sbox2/equiv/linear.py
cry/sbox2/equiv/linear_generic.py
cry/sbox2/equiv/test.py
cry/sbox2/generators/__init__.py
cry/sbox2/generators/feistel.py
cry/sbox2/generators/linear.py
cry/sbox2/generators/registry.py
cry/sbox2/generators/simple.py
cry/sbox2/sbox2.py
cry/sbox2/tables.py
cry/spaces.py
cry/utils/__init__.py
cry/utils/cache.py
cry-0.2.5.dist-info/METADATA
cry-0.2.5.dist-info/WHEEL
cry-0.2.5.dist-info/RECORD
