Metadata-Version: 2.3
Name: cry
Version: 0.2.5
Summary: Cry: SageMath/Python Toolkit for Cryptanalytic Research
License: MIT
Keywords: cryptanalysis,cryptography,S-Boxes
Author: Aleksei Udovenko
Author-email: aleksei@affine.group
Requires-Python: >=3.9
Classifier: Intended Audience :: Science/Research
Classifier: Topic :: Scientific/Engineering :: Mathematics
Classifier: Topic :: Security :: Cryptography
Classifier: Development Status :: 4 - Beta
Classifier: Programming Language :: Python
Requires-Dist: binteger (>=0.15.1)
Project-URL: Repository, http://github.com/hellman/cry
